[{"yAxis": "0.00", "xAxis": "2025-06-30"}, {"yAxis": "-0.89", "xAxis": "2025-07-01"}, {"yAxis": "-0.76", "xAxis": "2025-07-02"}, {"yAxis": "0.01", "xAxis": "2025-07-03"}, {"yAxis": "0.27", "xAxis": "2025-07-04"}, {"yAxis": "-1.09", "xAxis": "2025-07-07"}, {"yAxis": "0.60", "xAxis": "2025-07-08"}, {"yAxis": "0.37", "xAxis": "2025-07-09"}, {"yAxis": "0.83", "xAxis": "2025-07-10"}, {"yAxis": "1.33", "xAxis": "2025-07-11"}, {"yAxis": "0.85", "xAxis": "2025-07-14"}, {"yAxis": "2.45", "xAxis": "2025-07-15"}, {"yAxis": "2.34", "xAxis": "2025-07-16"}, {"yAxis": "3.67", "xAxis": "2025-07-17"}, {"yAxis": "3.60", "xAxis": "2025-07-18"}, {"yAxis": "3.42", "xAxis": "2025-07-21"}, {"yAxis": "3.05", "xAxis": "2025-07-22"}, {"yAxis": "2.73", "xAxis": "2025-07-23"}, {"yAxis": "3.54", "xAxis": "2025-07-24"}, {"yAxis": "4.74", "xAxis": "2025-07-25"}, {"yAxis": "6.14", "xAxis": "2025-07-28"}, {"yAxis": "7.67", "xAxis": "2025-07-29"}, {"yAxis": "6.91", "xAxis": "2025-07-30"}, {"yAxis": "5.62", "xAxis": "2025-07-31"}, {"yAxis": "4.16", "xAxis": "2025-08-01"}, {"yAxis": "6.42", "xAxis": "2025-08-04"}, {"yAxis": "5.88", "xAxis": "2025-08-05"}, {"yAxis": "5.99", "xAxis": "2025-08-06"}, {"yAxis": "6.61", "xAxis": "2025-08-07"}, {"yAxis": "6.47", "xAxis": "2025-08-08"}, {"yAxis": "6.78", "xAxis": "2025-08-11"}, {"yAxis": "10.08", "xAxis": "2025-08-12"}, {"yAxis": "11.45", "xAxis": "2025-08-13"}, {"yAxis": "11.21", "xAxis": "2025-08-14"}, {"yAxis": "11.08", "xAxis": "2025-08-15"}, {"yAxis": "11.59", "xAxis": "2025-08-18"}, {"yAxis": "9.53", "xAxis": "2025-08-19"}, {"yAxis": "9.82", "xAxis": "2025-08-20"}, {"yAxis": "9.30", "xAxis": "2025-08-21"}, {"yAxis": "14.23", "xAxis": "2025-08-22"}, {"yAxis": "15.12", "xAxis": "2025-08-25"}, {"yAxis": "14.89", "xAxis": "2025-08-26"}, {"yAxis": "15.69", "xAxis": "2025-08-27"}, {"yAxis": "19.21", "xAxis": "2025-08-28"}, {"yAxis": "16.00", "xAxis": "2025-08-29"}, {"yAxis": "16.91", "xAxis": "2025-09-01"}, {"yAxis": "14.57", "xAxis": "2025-09-02"}, {"yAxis": "14.65", "xAxis": "2025-09-03"}, {"yAxis": "12.37", "xAxis": "2025-09-04"}, {"yAxis": "15.21", "xAxis": "2025-09-05"}, {"yAxis": "14.47", "xAxis": "2025-09-08"}, {"yAxis": "14.51", "xAxis": "2025-09-09"}, {"yAxis": "15.17", "xAxis": "2025-09-10"}, {"yAxis": "18.20", "xAxis": "2025-09-11"}, {"yAxis": "18.82", "xAxis": "2025-09-12"}, {"yAxis": "19.35", "xAxis": "2025-09-15"}, {"yAxis": "19.84", "xAxis": "2025-09-16"}, {"yAxis": "20.71", "xAxis": "2025-09-17"}, {"yAxis": "24.49", "xAxis": "2025-09-18"}, {"yAxis": "24.12", "xAxis": "2025-09-19"}, {"yAxis": "25.87", "xAxis": "2025-09-22"}, {"yAxis": "25.20", "xAxis": "2025-09-23"}, {"yAxis": "26.26", "xAxis": "2025-09-24"}, {"yAxis": "27.02", "xAxis": "2025-09-25"}, {"yAxis": "25.97", "xAxis": "2025-09-26"}, {"yAxis": "27.19", "xAxis": "2025-09-29"}, {"yAxis": "29.00", "xAxis": "2025-09-30"}, {"yAxis": "34.88", "xAxis": "2025-10-09"}, {"yAxis": "27.97", "xAxis": "2025-10-10"}, {"yAxis": "32.08", "xAxis": "2025-10-13"}, {"yAxis": "27.87", "xAxis": "2025-10-14"}, {"yAxis": "30.53", "xAxis": "2025-10-15"}, {"yAxis": "30.85", "xAxis": "2025-10-16"}, {"yAxis": "29.32", "xAxis": "2025-10-17"}, {"yAxis": "31.45", "xAxis": "2025-10-20"}, {"yAxis": "33.00", "xAxis": "2025-10-21"}, {"yAxis": "31.68", "xAxis": "2025-10-22"}, {"yAxis": "32.54", "xAxis": "2025-10-23"}, {"yAxis": "37.01", "xAxis": "2025-10-24"}, {"yAxis": "40.48", "xAxis": "2025-10-27"}, {"yAxis": "40.84", "xAxis": "2025-10-28"}, {"yAxis": "41.84", "xAxis": "2025-10-29"}, {"yAxis": "39.67", "xAxis": "2025-10-30"}, {"yAxis": "37.84", "xAxis": "2025-10-31"}, {"yAxis": "37.82", "xAxis": "2025-11-03"}, {"yAxis": "34.34", "xAxis": "2025-11-04"}, {"yAxis": "35.72", "xAxis": "2025-11-05"}, {"yAxis": "37.16", "xAxis": "2025-11-06"}, {"yAxis": "35.63", "xAxis": "2025-11-07"}, {"yAxis": "37.74", "xAxis": "2025-11-10"}, {"yAxis": "34.80", "xAxis": "2025-11-11"}, {"yAxis": "35.61", "xAxis": "2025-11-12"}, {"yAxis": "33.58", "xAxis": "2025-11-13"}, {"yAxis": "32.13", "xAxis": "2025-11-14"}, {"yAxis": "30.86", "xAxis": "2025-11-17"}, {"yAxis": "29.51", "xAxis": "2025-11-18"}, {"yAxis": "30.47", "xAxis": "2025-11-19"}, {"yAxis": "27.26", "xAxis": "2025-11-20"}, {"yAxis": "24.92", "xAxis": "2025-11-21"}, {"yAxis": "28.46", "xAxis": "2025-11-24"}, {"yAxis": "29.24", "xAxis": "2025-11-25"}, {"yAxis": "32.48", "xAxis": "2025-11-26"}, {"yAxis": "32.02", "xAxis": "2025-11-27"}, {"yAxis": "33.70", "xAxis": "2025-11-28"}, {"yAxis": "34.43", "xAxis": "2025-12-01"}, {"yAxis": "34.99", "xAxis": "2025-12-02"}, {"yAxis": "36.12", "xAxis": "2025-12-03"}, {"yAxis": "36.70", "xAxis": "2025-12-04"}, {"yAxis": "38.07", "xAxis": "2025-12-05"}, {"yAxis": "40.65", "xAxis": "2025-12-08"}, {"yAxis": "40.95", "xAxis": "2025-12-09"}, {"yAxis": "42.58", "xAxis": "2025-12-10"}, {"yAxis": "40.83", "xAxis": "2025-12-11"}, {"yAxis": "37.38", "xAxis": "2025-12-12"}, {"yAxis": "35.46", "xAxis": "2025-12-15"}, {"yAxis": "34.38", "xAxis": "2025-12-16"}, {"yAxis": "33.45", "xAxis": "2025-12-17"}, {"yAxis": "34.31", "xAxis": "2025-12-18"}, {"yAxis": "36.33", "xAxis": "2025-12-19"}, {"yAxis": "39.21", "xAxis": "2025-12-22"}, {"yAxis": "40.39", "xAxis": "2025-12-23"}, {"yAxis": "41.08", "xAxis": "2025-12-24"}, {"yAxis": "40.88", "xAxis": "2025-12-25"}, {"yAxis": "40.66", "xAxis": "2025-12-26"}, {"yAxis": "41.10", "xAxis": "2025-12-29"}, {"yAxis": "41.25", "xAxis": "2025-12-30"}, {"yAxis": "39.51", "xAxis": "2025-12-31"}, {"yAxis": "45.34", "xAxis": "2026-01-05"}, {"yAxis": "47.33", "xAxis": "2026-01-06"}, {"yAxis": "46.89", "xAxis": "2026-01-07"}, {"yAxis": "45.11", "xAxis": "2026-01-08"}, {"yAxis": "48.06", "xAxis": "2026-01-09"}, {"yAxis": "48.51", "xAxis": "2026-01-12"}, {"yAxis": "47.25", "xAxis": "2026-01-13"}, {"yAxis": "47.43", "xAxis": "2026-01-14"}, {"yAxis": "50.32", "xAxis": "2026-01-15"}, {"yAxis": "52.92", "xAxis": "2026-01-16"}, {"yAxis": "52.85", "xAxis": "2026-01-19"}, {"yAxis": "49.87", "xAxis": "2026-01-20"}, {"yAxis": "53.62", "xAxis": "2026-01-21"}, {"yAxis": "54.47", "xAxis": "2026-01-22"}, {"yAxis": "52.35", "xAxis": "2026-01-23"}, {"yAxis": "51.63", "xAxis": "2026-01-26"}, {"yAxis": "55.42", "xAxis": "2026-01-27"}, {"yAxis": "57.86", "xAxis": "2026-01-28"}, {"yAxis": "55.83", "xAxis": "2026-01-29"}, {"yAxis": "54.19", "xAxis": "2026-01-30"}, {"yAxis": "53.47", "xAxis": "2026-02-02"}, {"yAxis": "51.69", "xAxis": "2026-02-03"}, {"yAxis": "45.92", "xAxis": "2026-02-04"}, {"yAxis": "44.72", "xAxis": "2026-02-05"}, {"yAxis": "48.90", "xAxis": "2026-02-06", "otherPoint": {"imageUrl": "https://img30.360buyimg.com/jr_image/jfs/t1/73797/17/20190/426/63636df0E0a0fca38/9bdf1636dc558a74.png", "managerPoint": "manager", "managerJump": {"jumpType": 2, "jumpUrl": "https://lc.jr.jd.com/finance/fund/latestdetail/fundArchives/?activeIndex=2&fundCode=017731&itemId=1017731"}, "managerName": "基金经理变更"}}, {"yAxis": "52.33", "xAxis": "2026-02-09"}, {"yAxis": "51.41", "xAxis": "2026-02-10"}, {"yAxis": "52.04", "xAxis": "2026-02-11"}, {"yAxis": "51.62", "xAxis": "2026-02-12"}, {"yAxis": "52.10", "xAxis": "2026-02-13"}, {"yAxis": "55.22", "xAxis": "2026-02-24"}, {"yAxis": "57.97", "xAxis": "2026-02-25"}, {"yAxis": "55.55", "xAxis": "2026-02-26"}, {"yAxis": "54.24", "xAxis": "2026-02-27"}, {"yAxis": "54.34", "xAxis": "2026-03-02"}, {"yAxis": "47.78", "xAxis": "2026-03-03"}, {"yAxis": "49.21", "xAxis": "2026-03-04"}, {"yAxis": "49.06", "xAxis": "2026-03-05"}, {"yAxis": "47.06", "xAxis": "2026-03-06"}, {"yAxis": "48.86", "xAxis": "2026-03-09"}, {"yAxis": "52.15", "xAxis": "2026-03-10"}, {"yAxis": "52.07", "xAxis": "2026-03-11"}, {"yAxis": "48.48", "xAxis": "2026-03-12"}, {"yAxis": "48.05", "xAxis": "2026-03-13"}, {"yAxis": "51.64", "xAxis": "2026-03-16"}, {"yAxis": "50.22", "xAxis": "2026-03-17"}, {"yAxis": "51.55", "xAxis": "2026-03-18"}, {"yAxis": "50.90", "xAxis": "2026-03-19"}, {"yAxis": "49.49", "xAxis": "2026-03-20"}, {"yAxis": "47.57", "xAxis": "2026-03-23"}, {"yAxis": "49.95", "xAxis": "2026-03-24"}, {"yAxis": "52.32", "xAxis": "2026-03-25"}, {"yAxis": "46.75", "xAxis": "2026-03-26"}, {"yAxis": "45.53", "xAxis": "2026-03-27"}, {"yAxis": "41.77", "xAxis": "2026-03-30"}, {"yAxis": "44.25", "xAxis": "2026-03-31"}, {"yAxis": "49.36", "xAxis": "2026-04-01"}, {"yAxis": "46.89", "xAxis": "2026-04-02"}, {"yAxis": "47.62", "xAxis": "2026-04-03"}, {"yAxis": "50.30", "xAxis": "2026-04-07"}, {"yAxis": "60.03", "xAxis": "2026-04-08"}, {"yAxis": "61.98", "xAxis": "2026-04-09"}, {"yAxis": "65.96", "xAxis": "2026-04-10"}, {"yAxis": "67.64", "xAxis": "2026-04-13"}, {"yAxis": "71.26", "xAxis": "2026-04-14"}, {"yAxis": "70.88", "xAxis": "2026-04-15"}, {"yAxis": "72.79", "xAxis": "2026-04-16"}, {"yAxis": "75.92", "xAxis": "2026-04-17"}, {"yAxis": "76.84", "xAxis": "2026-04-20"}, {"yAxis": "76.79", "xAxis": "2026-04-21"}, {"yAxis": "81.75", "xAxis": "2026-04-22"}, {"yAxis": "82.20", "xAxis": "2026-04-23"}, {"yAxis": "87.79", "xAxis": "2026-04-24"}, {"yAxis": "89.49", "xAxis": "2026-04-27"}, {"yAxis": "85.81", "xAxis": "2026-04-28"}, {"yAxis": "88.14", "xAxis": "2026-04-29"}, {"yAxis": "94.34", "xAxis": "2026-04-30"}, {"yAxis": "104.55", "xAxis": "2026-05-06"}, {"yAxis": "104.04", "xAxis": "2026-05-07"}, {"yAxis": "107.00", "xAxis": "2026-05-08"}, {"yAxis": "112.93", "xAxis": "2026-05-11"}, {"yAxis": "111.86", "xAxis": "2026-05-12"}, {"yAxis": "117.00", "xAxis": "2026-05-13"}, {"yAxis": "115.82", "xAxis": "2026-05-14"}, {"yAxis": "110.38", "xAxis": "2026-05-15"}, {"yAxis": "108.97", "xAxis": "2026-05-18"}, {"yAxis": "110.97", "xAxis": "2026-05-19"}, {"yAxis": "121.19", "xAxis": "2026-05-20"}, {"yAxis": "116.95", "xAxis": "2026-05-21"}, {"yAxis": "121.72", "xAxis": "2026-05-22"}, {"yAxis": "125.34", "xAxis": "2026-05-25"}, {"yAxis": "129.35", "xAxis": "2026-05-26"}, {"yAxis": "128.05", "xAxis": "2026-05-27"}, {"yAxis": "131.05", "xAxis": "2026-05-28"}, {"yAxis": "125.79", "xAxis": "2026-05-29"}, {"yAxis": "122.89", "xAxis": "2026-06-01"}, {"yAxis": "131.64", "xAxis": "2026-06-02"}, {"yAxis": "135.84", "xAxis": "2026-06-03"}, {"yAxis": "135.46", "xAxis": "2026-06-04"}, {"yAxis": "121.54", "xAxis": "2026-06-05"}, {"yAxis": "122.77", "xAxis": "2026-06-08"}, {"yAxis": "126.99", "xAxis": "2026-06-09"}, {"yAxis": "121.57", "xAxis": "2026-06-10"}, {"yAxis": "129.00", "xAxis": "2026-06-11"}, {"yAxis": "129.67", "xAxis": "2026-06-12"}, {"yAxis": "142.14", "xAxis": "2026-06-15"}, {"yAxis": "139.17", "xAxis": "2026-06-16"}, {"yAxis": "144.77", "xAxis": "2026-06-17"}, {"yAxis": "154.58", "xAxis": "2026-06-18"}, {"yAxis": "159.24", "xAxis": "2026-06-22"}, {"yAxis": "149.15", "xAxis": "2026-06-23"}, {"yAxis": "155.38", "xAxis": "2026-06-24"}, {"yAxis": "165.34", "xAxis": "2026-06-25"}, {"yAxis": "157.80", "xAxis": "2026-06-26"}, {"yAxis": "164.77", "xAxis": "2026-06-29"}, {"yAxis": "176.41", "xAxis": "2026-06-30"}]