[{"xAxis": "2025-07-04", "yAxis": 0.0}, {"xAxis": "2025-07-07", "yAxis": -0.01}, {"xAxis": "2025-07-08", "yAxis": 0.1}, {"xAxis": "2025-07-09", "yAxis": 0.05}, {"xAxis": "2025-07-10", "yAxis": 0.05}, {"xAxis": "2025-07-11", "yAxis": 0.03}, {"xAxis": "2025-07-14", "yAxis": 0.16}, {"xAxis": "2025-07-15", "yAxis": 1.35}, {"xAxis": "2025-07-16", "yAxis": 1.34}, {"xAxis": "2025-07-17", "yAxis": 1.96}, {"xAxis": "2025-07-18", "yAxis": 2.11}, {"xAxis": "2025-07-21", "yAxis": 1.98}, {"xAxis": "2025-07-22", "yAxis": 1.89}, {"xAxis": "2025-07-23", "yAxis": 2.38}, {"xAxis": "2025-07-24", "yAxis": 2.49}, {"xAxis": "2025-07-25", "yAxis": 2.84}, {"xAxis": "2025-07-28", "yAxis": 2.94}, {"xAxis": "2025-07-29", "yAxis": 4.2}, {"xAxis": "2025-07-30", "yAxis": 3.58}, {"xAxis": "2025-07-31", "yAxis": 3.83}, {"xAxis": "2025-08-01", "yAxis": 3.23}, {"xAxis": "2025-08-04", "yAxis": 3.87}, {"xAxis": "2025-08-05", "yAxis": 4.27}, {"xAxis": "2025-08-06", "yAxis": 4.76}, {"xAxis": "2025-08-07", "yAxis": 4.75}, {"xAxis": "2025-08-08", "yAxis": 3.65}, {"xAxis": "2025-08-11", "yAxis": 6.25}, {"xAxis": "2025-08-12", "yAxis": 7.17}, {"xAxis": "2025-08-13", "yAxis": 13.09}, {"xAxis": "2025-08-14", "yAxis": 10.19}, {"xAxis": "2025-08-15", "yAxis": 10.49}, {"xAxis": "2025-08-18", "yAxis": 13.99}, {"xAxis": "2025-08-19", "yAxis": 16.77}, {"xAxis": "2025-08-20", "yAxis": 16.22}, {"xAxis": "2025-08-21", "yAxis": 14.32}, {"xAxis": "2025-08-22", "yAxis": 18.14}, {"xAxis": "2025-08-25", "yAxis": 25.43}, {"xAxis": "2025-08-26", "yAxis": 24.62}, {"xAxis": "2025-08-27", "yAxis": 27.81}, {"xAxis": "2025-08-28", "yAxis": 39.06}, {"xAxis": "2025-08-29", "yAxis": 38.73}, {"xAxis": "2025-09-01", "yAxis": 44.3}, {"xAxis": "2025-09-02", "yAxis": 35.96}, {"xAxis": "2025-09-03", "yAxis": 38.88}, {"xAxis": "2025-09-04", "yAxis": 26.22}, {"xAxis": "2025-09-05", "yAxis": 34.57}, {"xAxis": "2025-09-08", "yAxis": 28.33}, {"xAxis": "2025-09-09", "yAxis": 25.93}, {"xAxis": "2025-09-10", "yAxis": 30.8}, {"xAxis": "2025-09-11", "yAxis": 42.23}, {"xAxis": "2025-09-12", "yAxis": 39.28}, {"xAxis": "2025-09-15", "yAxis": 37.02}, {"xAxis": "2025-09-16", "yAxis": 38.15}, {"xAxis": "2025-09-17", "yAxis": 38.87}, {"xAxis": "2025-09-18", "yAxis": 41.19}, {"xAxis": "2025-09-19", "yAxis": 41.35}, {"xAxis": "2025-09-22", "yAxis": 42.96}, {"xAxis": "2025-09-23", "yAxis": 42.59}, {"xAxis": "2025-09-24", "yAxis": 41.21}, {"xAxis": "2025-09-25", "yAxis": 42.85}, {"xAxis": "2025-09-26", "yAxis": 36.87}, {"xAxis": "2025-09-29", "yAxis": 40.07}, {"xAxis": "2025-09-30", "yAxis": 38.5}, {"xAxis": "2025-10-09", "yAxis": 38.55}, {"xAxis": "2025-10-10", "yAxis": 34.2}, {"xAxis": "2025-10-13", "yAxis": 32.34}, {"xAxis": "2025-10-14", "yAxis": 25.57}, {"xAxis": "2025-10-15", "yAxis": 28.8}, {"xAxis": "2025-10-16", "yAxis": 28.62}, {"xAxis": "2025-10-17", "yAxis": 23.72}, {"xAxis": "2025-10-20", "yAxis": 28.28}, {"xAxis": "2025-10-21", "yAxis": 36.39}, {"xAxis": "2025-10-22", "yAxis": 36.81}, {"xAxis": "2025-10-23", "yAxis": 33.89}, {"xAxis": "2025-10-24", "yAxis": 42.11}, {"xAxis": "2025-10-27", "yAxis": 49.59}, {"xAxis": "2025-10-28", "yAxis": 49.71}, {"xAxis": "2025-10-29", "yAxis": 50.79}, {"xAxis": "2025-10-30", "yAxis": 45.21}, {"xAxis": "2025-10-31", "yAxis": 38.11}, {"xAxis": "2025-11-03", "yAxis": 38.03}, {"xAxis": "2025-11-04", "yAxis": 36.6}, {"xAxis": "2025-11-05", "yAxis": 36.14}, {"xAxis": "2025-11-06", "yAxis": 41.93}, {"xAxis": "2025-11-07", "yAxis": 40.9}, {"xAxis": "2025-11-10", "yAxis": 39.23}, {"xAxis": "2025-11-11", "yAxis": 36.43}, {"xAxis": "2025-11-12", "yAxis": 36.11}, {"xAxis": "2025-11-13", "yAxis": 35.9}, {"xAxis": "2025-11-14", "yAxis": 31.37}, {"xAxis": "2025-11-17", "yAxis": 32.61}, {"xAxis": "2025-11-18", "yAxis": 32.86}, {"xAxis": "2025-11-19", "yAxis": 33.75}, {"xAxis": "2025-11-20", "yAxis": 34.63}, {"xAxis": "2025-11-21", "yAxis": 27.18}, {"xAxis": "2025-11-24", "yAxis": 26.25}, {"xAxis": "2025-11-25", "yAxis": 31.88}, {"xAxis": "2025-11-26", "yAxis": 37.24}, {"xAxis": "2025-11-27", "yAxis": 36.5}, {"xAxis": "2025-11-28", "yAxis": 36.8}, {"xAxis": "2025-12-01", "yAxis": 38.34}, {"xAxis": "2025-12-02", "yAxis": 37.97}, {"xAxis": "2025-12-03", "yAxis": 38.07}, {"xAxis": "2025-12-04", "yAxis": 39.24}, {"xAxis": "2025-12-05", "yAxis": 40.78}, {"xAxis": "2025-12-08", "yAxis": 48.58}, {"xAxis": "2025-12-09", "yAxis": 53.11}, {"xAxis": "2025-12-10", "yAxis": 53.58}, {"xAxis": "2025-12-11", "yAxis": 49.11}, {"xAxis": "2025-12-12", "yAxis": 52.34}, {"xAxis": "2025-12-15", "yAxis": 47.7}, {"xAxis": "2025-12-16", "yAxis": 44.58}, {"xAxis": "2025-12-17", "yAxis": 52.83}, {"xAxis": "2025-12-18", "yAxis": 48.48}, {"xAxis": "2025-12-19", "yAxis": 47.51}, {"xAxis": "2025-12-22", "yAxis": 55.13}, {"xAxis": "2025-12-23", "yAxis": 56.12}, {"xAxis": "2025-12-24", "yAxis": 59.11}, {"xAxis": "2025-12-25", "yAxis": 58.18}, {"xAxis": "2025-12-26", "yAxis": 56.56}, {"xAxis": "2025-12-29", "yAxis": 57.67}, {"xAxis": "2025-12-30", "yAxis": 57.18}, {"xAxis": "2025-12-31", "yAxis": 54.13}, {"xAxis": "2026-01-05", "yAxis": 57.71}, {"xAxis": "2026-01-06", "yAxis": 55.69}, {"xAxis": "2026-01-07", "yAxis": 57.8}, {"xAxis": "2026-01-08", "yAxis": 54.81}, {"xAxis": "2026-01-09", "yAxis": 54.86}, {"xAxis": "2026-01-12", "yAxis": 53.64}, {"xAxis": "2026-01-13", "yAxis": 49.57}, {"xAxis": "2026-01-14", "yAxis": 52.43}, {"xAxis": "2026-01-15", "yAxis": 56.15}, {"xAxis": "2026-01-16", "yAxis": 57.46}, {"xAxis": "2026-01-19", "yAxis": 56.32}, {"xAxis": "2026-01-20", "yAxis": 50.76}, {"xAxis": "2026-01-21", "yAxis": 54.84}, {"xAxis": "2026-01-22", "yAxis": 58.94}, {"xAxis": "2026-01-23", "yAxis": 53.86}, {"xAxis": "2026-01-26", "yAxis": 53.42}, {"xAxis": "2026-01-27", "yAxis": 57.69}, {"xAxis": "2026-01-28", "yAxis": 59.5}, {"xAxis": "2026-01-29", "yAxis": 56.24}, {"xAxis": "2026-01-30", "yAxis": 60.77}, {"xAxis": "2026-02-02", "yAxis": 56.37}, {"xAxis": "2026-02-03", "yAxis": 58.88}, {"xAxis": "2026-02-04", "yAxis": 54.55}, {"xAxis": "2026-02-05", "yAxis": 50.43}, {"xAxis": "2026-02-06", "yAxis": 49.5}, {"xAxis": "2026-02-09", "yAxis": 58.08}, {"xAxis": "2026-02-10", "yAxis": 58.01}, {"xAxis": "2026-02-11", "yAxis": 54.27}, {"xAxis": "2026-02-12", "yAxis": 58.84}, {"xAxis": "2026-02-13", "yAxis": 55.67}, {"xAxis": "2026-02-24", "yAxis": 61.45}, {"xAxis": "2026-02-25", "yAxis": 63.43}, {"xAxis": "2026-02-26", "yAxis": 69.63}, {"xAxis": "2026-02-27", "yAxis": 64.52}, {"xAxis": "2026-03-02", "yAxis": 68.09}, {"xAxis": "2026-03-03", "yAxis": 64.35}, {"xAxis": "2026-03-04", "yAxis": 62.04}, {"xAxis": "2026-03-05", "yAxis": 63.32}, {"xAxis": "2026-03-06", "yAxis": 61.31}, {"xAxis": "2026-03-09", "yAxis": 56.14}, {"xAxis": "2026-03-10", "yAxis": 65.4}, {"xAxis": "2026-03-11", "yAxis": 64.58}, {"xAxis": "2026-03-12", "yAxis": 62.5}, {"xAxis": "2026-03-13", "yAxis": 63.05}, {"xAxis": "2026-03-16", "yAxis": 66.37}, {"xAxis": "2026-03-17", "yAxis": 58.23}, {"xAxis": "2026-03-18", "yAxis": 64.84}, {"xAxis": "2026-03-19", "yAxis": 63.19}, {"xAxis": "2026-03-20", "yAxis": 68.18}, {"xAxis": "2026-03-23", "yAxis": 59.79}, {"xAxis": "2026-03-24", "yAxis": 63.01}, {"xAxis": "2026-03-25", "yAxis": 68.13}, {"xAxis": "2026-03-26", "yAxis": 64.99}, {"xAxis": "2026-03-27", "yAxis": 64.19}, {"xAxis": "2026-03-30", "yAxis": 64.74}, {"xAxis": "2026-03-31", "yAxis": 59.48}, {"xAxis": "2026-04-01", "yAxis": 66.59}, {"xAxis": "2026-04-02", "yAxis": 63.0}, {"xAxis": "2026-04-03", "yAxis": 67.58}, {"xAxis": "2026-04-07", "yAxis": 68.87}, {"xAxis": "2026-04-08", "yAxis": 82.41}, {"xAxis": "2026-04-09", "yAxis": 86.06}, {"xAxis": "2026-04-10", "yAxis": 93.36}, {"xAxis": "2026-04-13", "yAxis": 96.15}, {"xAxis": "2026-04-14", "yAxis": 99.67}, {"xAxis": "2026-04-15", "yAxis": 97.71}, {"xAxis": "2026-04-16", "yAxis": 101.57}, {"xAxis": "2026-04-17", "yAxis": 111.08}, {"xAxis": "2026-04-20", "yAxis": 110.81}, {"xAxis": "2026-04-21", "yAxis": 113.53}, {"xAxis": "2026-04-22", "yAxis": 122.61}, {"xAxis": "2026-04-23", "yAxis": 118.04}, {"xAxis": "2026-04-24", "yAxis": 113.81}, {"xAxis": "2026-04-27", "yAxis": 118.52}, {"xAxis": "2026-04-28", "yAxis": 114.63}, {"xAxis": "2026-04-29", "yAxis": 117.01}, {"xAxis": "2026-04-30", "yAxis": 118.46}, {"xAxis": "2026-05-06", "yAxis": 123.9}, {"xAxis": "2026-05-07", "yAxis": 134.78}, {"xAxis": "2026-05-08", "yAxis": 135.92}, {"xAxis": "2026-05-11", "yAxis": 142.37}, {"xAxis": "2026-05-12", "yAxis": 148.54}, {"xAxis": "2026-05-13", "yAxis": 155.61}, {"xAxis": "2026-05-14", "yAxis": 150.87}, {"xAxis": "2026-05-15", "yAxis": 142.57}, {"xAxis": "2026-05-18", "yAxis": 144.44}, {"xAxis": "2026-05-19", "yAxis": 142.27}, {"xAxis": "2026-05-20", "yAxis": 145.71}, {"xAxis": "2026-05-21", "yAxis": 134.66}, {"xAxis": "2026-05-22", "yAxis": 149.75}, {"xAxis": "2026-05-25", "yAxis": 161.04}, {"xAxis": "2026-05-26", "yAxis": 163.47}, {"xAxis": "2026-05-27", "yAxis": 162.27}, {"xAxis": "2026-05-28", "yAxis": 171.57}, {"xAxis": "2026-05-29", "yAxis": 167.91}, {"xAxis": "2026-06-01", "yAxis": 152.45}, {"xAxis": "2026-06-02", "yAxis": 167.98}, {"xAxis": "2026-06-03", "yAxis": 177.9}, {"xAxis": "2026-06-04", "yAxis": 181.17}, {"xAxis": "2026-06-05", "yAxis": 170.08}, {"xAxis": "2026-06-08", "yAxis": 164.12}, {"xAxis": "2026-06-09", "yAxis": 178.66}, {"xAxis": "2026-06-10", "yAxis": 170.66}, {"xAxis": "2026-06-11", "yAxis": 170.93}, {"xAxis": "2026-06-12", "yAxis": 168.42}, {"xAxis": "2026-06-15", "yAxis": 189.3}, {"xAxis": "2026-06-16", "yAxis": 202.5}, {"xAxis": "2026-06-17", "yAxis": 209.23}, {"xAxis": "2026-06-18", "yAxis": 217.11}, {"xAxis": "2026-06-22", "yAxis": 220.89}, {"xAxis": "2026-06-23", "yAxis": 205.94}, {"xAxis": "2026-06-24", "yAxis": 215.39}, {"xAxis": "2026-06-25", "yAxis": 228.22}, {"xAxis": "2026-06-26", "yAxis": 213.17}, {"xAxis": "2026-06-29", "yAxis": 207.46}, {"xAxis": "2026-06-30", "yAxis": 223.76}, {"xAxis": "2026-07-01", "yAxis": 209.29}, {"xAxis": "2026-07-02", "yAxis": 186.2}, {"xAxis": "2026-07-03", "yAxis": 189.14}, {"xAxis": "2026-07-06", "yAxis": 177.49}, {"xAxis": "2026-07-07", "yAxis": 176.42}, {"xAxis": "2026-07-08", "yAxis": 172.03}, {"xAxis": "2026-07-09", "yAxis": 189.38}, {"xAxis": "2026-07-10", "yAxis": 174.49}, {"xAxis": "2026-07-13", "yAxis": 161.61}, {"xAxis": "2026-07-14", "yAxis": 182.62}, {"xAxis": "2026-07-15", "yAxis": 177.59}, {"xAxis": "2026-07-16", "yAxis": 169.15}, {"xAxis": "2026-07-17", "yAxis": 145.47}, {"xAxis": "2026-07-20", "yAxis": 130.3}, {"xAxis": "2026-07-21", "yAxis": 150.27}]