[{"yAxis": "0.00", "xAxis": "2025-06-30"}, {"yAxis": "0.16", "xAxis": "2025-07-01"}, {"yAxis": "1.94", "xAxis": "2025-07-02"}, {"yAxis": "2.17", "xAxis": "2025-07-03"}, {"yAxis": "2.03", "xAxis": "2025-07-04"}, {"yAxis": "1.36", "xAxis": "2025-07-07"}, {"yAxis": "1.26", "xAxis": "2025-07-08"}, {"yAxis": "0.84", "xAxis": "2025-07-09"}, {"yAxis": "1.81", "xAxis": "2025-07-10"}, {"yAxis": "2.25", "xAxis": "2025-07-11"}, {"yAxis": "1.80", "xAxis": "2025-07-14"}, {"yAxis": "0.54", "xAxis": "2025-07-15"}, {"yAxis": "0.07", "xAxis": "2025-07-16"}, {"yAxis": "0.00", "xAxis": "2025-07-17"}, {"yAxis": "0.49", "xAxis": "2025-07-18"}, {"yAxis": "1.27", "xAxis": "2025-07-21"}, {"yAxis": "2.69", "xAxis": "2025-07-22"}, {"yAxis": "3.15", "xAxis": "2025-07-23"}, {"yAxis": "2.75", "xAxis": "2025-07-24"}, {"yAxis": "2.33", "xAxis": "2025-07-25"}, {"yAxis": "2.11", "xAxis": "2025-07-28"}, {"yAxis": "2.55", "xAxis": "2025-07-29"}, {"yAxis": "0.95", "xAxis": "2025-07-30"}, {"yAxis": "0.13", "xAxis": "2025-07-31"}, {"yAxis": "-0.39", "xAxis": "2025-08-01"}, {"yAxis": "0.67", "xAxis": "2025-08-04"}, {"yAxis": "1.87", "xAxis": "2025-08-05"}, {"yAxis": "2.00", "xAxis": "2025-08-06"}, {"yAxis": "2.05", "xAxis": "2025-08-07"}, {"yAxis": "2.84", "xAxis": "2025-08-08"}, {"yAxis": "2.34", "xAxis": "2025-08-11"}, {"yAxis": "3.07", "xAxis": "2025-08-12"}, {"yAxis": "3.43", "xAxis": "2025-08-13"}, {"yAxis": "2.94", "xAxis": "2025-08-14"}, {"yAxis": "3.54", "xAxis": "2025-08-15"}, {"yAxis": "2.75", "xAxis": "2025-08-18"}, {"yAxis": "2.20", "xAxis": "2025-08-19"}, {"yAxis": "2.76", "xAxis": "2025-08-20"}, {"yAxis": "3.55", "xAxis": "2025-08-21"}, {"yAxis": "5.12", "xAxis": "2025-08-22"}, {"yAxis": "5.66", "xAxis": "2025-08-25"}, {"yAxis": "5.96", "xAxis": "2025-08-26"}, {"yAxis": "6.14", "xAxis": "2025-08-27"}, {"yAxis": "6.49", "xAxis": "2025-08-28"}, {"yAxis": "7.40", "xAxis": "2025-08-29"}, {"yAxis": "7.88", "xAxis": "2025-09-01"}, {"yAxis": "8.40", "xAxis": "2025-09-02"}, {"yAxis": "8.41", "xAxis": "2025-09-03"}, {"yAxis": "7.80", "xAxis": "2025-09-04"}, {"yAxis": "8.44", "xAxis": "2025-09-05"}, {"yAxis": "8.95", "xAxis": "2025-09-08"}, {"yAxis": "8.88", "xAxis": "2025-09-09"}, {"yAxis": "9.74", "xAxis": "2025-09-10"}, {"yAxis": "10.34", "xAxis": "2025-09-11"}, {"yAxis": "10.38", "xAxis": "2025-09-12"}, {"yAxis": "10.95", "xAxis": "2025-09-15"}, {"yAxis": "11.18", "xAxis": "2025-09-16"}, {"yAxis": "10.73", "xAxis": "2025-09-17"}, {"yAxis": "10.60", "xAxis": "2025-09-18"}, {"yAxis": "11.57", "xAxis": "2025-09-19"}, {"yAxis": "12.38", "xAxis": "2025-09-22"}, {"yAxis": "13.38", "xAxis": "2025-09-23"}, {"yAxis": "13.38", "xAxis": "2025-09-24"}, {"yAxis": "14.10", "xAxis": "2025-09-25"}, {"yAxis": "15.10", "xAxis": "2025-09-26"}, {"yAxis": "15.32", "xAxis": "2025-09-29"}, {"yAxis": "15.32", "xAxis": "2025-09-30"}, {"yAxis": "16.18", "xAxis": "2025-10-09"}, {"yAxis": "13.76", "xAxis": "2025-10-10"}, {"yAxis": "15.72", "xAxis": "2025-10-13"}, {"yAxis": "15.01", "xAxis": "2025-10-14"}, {"yAxis": "16.65", "xAxis": "2025-10-15"}, {"yAxis": "17.07", "xAxis": "2025-10-16"}, {"yAxis": "14.25", "xAxis": "2025-10-17"}, {"yAxis": "15.75", "xAxis": "2025-10-20"}, {"yAxis": "12.17", "xAxis": "2025-10-21"}, {"yAxis": "12.69", "xAxis": "2025-10-22"}, {"yAxis": "14.49", "xAxis": "2025-10-23"}, {"yAxis": "14.30", "xAxis": "2025-10-24"}, {"yAxis": "13.58", "xAxis": "2025-10-27"}, {"yAxis": "13.43", "xAxis": "2025-10-28"}, {"yAxis": "14.15", "xAxis": "2025-10-29"}, {"yAxis": "14.66", "xAxis": "2025-10-30"}, {"yAxis": "14.06", "xAxis": "2025-10-31"}, {"yAxis": "13.87", "xAxis": "2025-11-03"}, {"yAxis": "11.18", "xAxis": "2025-11-04"}, {"yAxis": "12.65", "xAxis": "2025-11-05"}, {"yAxis": "13.68", "xAxis": "2025-11-06"}, {"yAxis": "14.79", "xAxis": "2025-11-07"}, {"yAxis": "17.30", "xAxis": "2025-11-10"}, {"yAxis": "18.24", "xAxis": "2025-11-11"}, {"yAxis": "19.34", "xAxis": "2025-11-12"}, {"yAxis": "18.62", "xAxis": "2025-11-13"}, {"yAxis": "18.54", "xAxis": "2025-11-14"}, {"yAxis": "17.20", "xAxis": "2025-11-17"}, {"yAxis": "16.81", "xAxis": "2025-11-18"}, {"yAxis": "17.08", "xAxis": "2025-11-19"}, {"yAxis": "15.00", "xAxis": "2025-11-20"}, {"yAxis": "14.49", "xAxis": "2025-11-21"}, {"yAxis": "16.29", "xAxis": "2025-11-24"}, {"yAxis": "16.56", "xAxis": "2025-11-25"}, {"yAxis": "18.68", "xAxis": "2025-11-26"}, {"yAxis": "18.76", "xAxis": "2025-11-27"}, {"yAxis": "19.98", "xAxis": "2025-11-28"}, {"yAxis": "20.87", "xAxis": "2025-12-01"}, {"yAxis": "19.82", "xAxis": "2025-12-02"}, {"yAxis": "20.85", "xAxis": "2025-12-03"}, {"yAxis": "21.46", "xAxis": "2025-12-04"}, {"yAxis": "21.47", "xAxis": "2025-12-05"}, {"yAxis": "20.32", "xAxis": "2025-12-08"}, {"yAxis": "20.36", "xAxis": "2025-12-09"}, {"yAxis": "21.09", "xAxis": "2025-12-10"}, {"yAxis": "22.32", "xAxis": "2025-12-11"}, {"yAxis": "21.72", "xAxis": "2025-12-12"}, {"yAxis": "21.55", "xAxis": "2025-12-15"}, {"yAxis": "19.60", "xAxis": "2025-12-16"}, {"yAxis": "20.79", "xAxis": "2025-12-17"}, {"yAxis": "20.52", "xAxis": "2025-12-18"}, {"yAxis": "21.64", "xAxis": "2025-12-19"}, {"yAxis": "23.66", "xAxis": "2025-12-22"}, {"yAxis": "24.21", "xAxis": "2025-12-23"}, {"yAxis": "24.06", "xAxis": "2025-12-24"}, {"yAxis": "23.92", "xAxis": "2025-12-25"}, {"yAxis": "24.24", "xAxis": "2025-12-26"}, {"yAxis": "22.29", "xAxis": "2025-12-29"}, {"yAxis": "23.51", "xAxis": "2025-12-30"}, {"yAxis": "22.67", "xAxis": "2025-12-31"}, {"yAxis": "25.90", "xAxis": "2026-01-05"}, {"yAxis": "27.69", "xAxis": "2026-01-06"}, {"yAxis": "26.92", "xAxis": "2026-01-07"}, {"yAxis": "27.11", "xAxis": "2026-01-08"}, {"yAxis": "28.46", "xAxis": "2026-01-09"}, {"yAxis": "30.33", "xAxis": "2026-01-12"}, {"yAxis": "31.93", "xAxis": "2026-01-13"}, {"yAxis": "33.40", "xAxis": "2026-01-14"}, {"yAxis": "33.19", "xAxis": "2026-01-15"}, {"yAxis": "32.70", "xAxis": "2026-01-16"}, {"yAxis": "32.94", "xAxis": "2026-01-19"}, {"yAxis": "34.41", "xAxis": "2026-01-20"}, {"yAxis": "35.79", "xAxis": "2026-01-21"}, {"yAxis": "35.75", "xAxis": "2026-01-22"}, {"yAxis": "37.55", "xAxis": "2026-01-23"}, {"yAxis": "38.68", "xAxis": "2026-01-26"}, {"yAxis": "39.89", "xAxis": "2026-01-27"}, {"yAxis": "41.91", "xAxis": "2026-01-28"}, {"yAxis": "41.72", "xAxis": "2026-01-29"}, {"yAxis": "35.79", "xAxis": "2026-01-30"}, {"yAxis": "34.57", "xAxis": "2026-02-02"}, {"yAxis": "38.84", "xAxis": "2026-02-03"}, {"yAxis": "38.67", "xAxis": "2026-02-04"}, {"yAxis": "34.38", "xAxis": "2026-02-05"}, {"yAxis": "36.85", "xAxis": "2026-02-06"}, {"yAxis": "40.40", "xAxis": "2026-02-09"}, {"yAxis": "40.85", "xAxis": "2026-02-10"}, {"yAxis": "44.16", "xAxis": "2026-02-11"}, {"yAxis": "41.05", "xAxis": "2026-02-12"}, {"yAxis": "41.52", "xAxis": "2026-02-13"}, {"yAxis": "47.11", "xAxis": "2026-02-24"}, {"yAxis": "48.34", "xAxis": "2026-02-25"}, {"yAxis": "48.75", "xAxis": "2026-02-26"}, {"yAxis": "50.39", "xAxis": "2026-02-27"}, {"yAxis": "52.01", "xAxis": "2026-03-02"}, {"yAxis": "45.99", "xAxis": "2026-03-03"}, {"yAxis": "46.15", "xAxis": "2026-03-04"}, {"yAxis": "43.81", "xAxis": "2026-03-05"}, {"yAxis": "42.88", "xAxis": "2026-03-06"}, {"yAxis": "42.79", "xAxis": "2026-03-09"}, {"yAxis": "43.62", "xAxis": "2026-03-10"}, {"yAxis": "44.47", "xAxis": "2026-03-11"}, {"yAxis": "44.21", "xAxis": "2026-03-12"}, {"yAxis": "41.41", "xAxis": "2026-03-13"}, {"yAxis": "42.26", "xAxis": "2026-03-16"}, {"yAxis": "42.87", "xAxis": "2026-03-17"}, {"yAxis": "41.17", "xAxis": "2026-03-18"}, {"yAxis": "38.62", "xAxis": "2026-03-19"}, {"yAxis": "36.59", "xAxis": "2026-03-20"}, {"yAxis": "37.25", "xAxis": "2026-03-23"}, {"yAxis": "40.06", "xAxis": "2026-03-24"}, {"yAxis": "41.70", "xAxis": "2026-03-25"}, {"yAxis": "41.00", "xAxis": "2026-03-26"}, {"yAxis": "43.23", "xAxis": "2026-03-27"}, {"yAxis": "43.05", "xAxis": "2026-03-30"}, {"yAxis": "44.17", "xAxis": "2026-03-31"}, {"yAxis": "43.96", "xAxis": "2026-04-01"}, {"yAxis": "44.11", "xAxis": "2026-04-02"}, {"yAxis": "44.18", "xAxis": "2026-04-03"}, {"yAxis": "45.14", "xAxis": "2026-04-07"}, {"yAxis": "44.45", "xAxis": "2026-04-08"}, {"yAxis": "43.81", "xAxis": "2026-04-09"}, {"yAxis": "44.68", "xAxis": "2026-04-10"}, {"yAxis": "44.85", "xAxis": "2026-04-13"}, {"yAxis": "44.21", "xAxis": "2026-04-14"}, {"yAxis": "42.76", "xAxis": "2026-04-15"}, {"yAxis": "44.28", "xAxis": "2026-04-16"}, {"yAxis": "42.16", "xAxis": "2026-04-17"}, {"yAxis": "42.04", "xAxis": "2026-04-20"}, {"yAxis": "41.27", "xAxis": "2026-04-21"}, {"yAxis": "42.75", "xAxis": "2026-04-22"}, {"yAxis": "42.18", "xAxis": "2026-04-23"}, {"yAxis": "42.37", "xAxis": "2026-04-24"}, {"yAxis": "41.73", "xAxis": "2026-04-27"}, {"yAxis": "41.16", "xAxis": "2026-04-28"}, {"yAxis": "42.18", "xAxis": "2026-04-29"}, {"yAxis": "43.69", "xAxis": "2026-04-30"}, {"yAxis": "43.34", "xAxis": "2026-05-06"}, {"yAxis": "41.98", "xAxis": "2026-05-07"}, {"yAxis": "42.72", "xAxis": "2026-05-08"}, {"yAxis": "45.37", "xAxis": "2026-05-11"}, {"yAxis": "46.13", "xAxis": "2026-05-12"}, {"yAxis": "46.74", "xAxis": "2026-05-13"}, {"yAxis": "45.81", "xAxis": "2026-05-14"}, {"yAxis": "43.08", "xAxis": "2026-05-15"}, {"yAxis": "43.39", "xAxis": "2026-05-18"}, {"yAxis": "42.27", "xAxis": "2026-05-19"}, {"yAxis": "42.04", "xAxis": "2026-05-20"}, {"yAxis": "41.86", "xAxis": "2026-05-21"}, {"yAxis": "42.29", "xAxis": "2026-05-22"}, {"yAxis": "42.15", "xAxis": "2026-05-25"}, {"yAxis": "42.81", "xAxis": "2026-05-26"}, {"yAxis": "40.31", "xAxis": "2026-05-27"}, {"yAxis": "40.80", "xAxis": "2026-05-28"}, {"yAxis": "40.76", "xAxis": "2026-05-29"}, {"yAxis": "41.63", "xAxis": "2026-06-01"}, {"yAxis": "44.44", "xAxis": "2026-06-02"}, {"yAxis": "43.94", "xAxis": "2026-06-03"}, {"yAxis": "43.37", "xAxis": "2026-06-04"}, {"yAxis": "37.56", "xAxis": "2026-06-05"}, {"yAxis": "37.56", "xAxis": "2026-06-08"}, {"yAxis": "35.47", "xAxis": "2026-06-09"}, {"yAxis": "34.54", "xAxis": "2026-06-10"}, {"yAxis": "36.10", "xAxis": "2026-06-11"}, {"yAxis": "38.62", "xAxis": "2026-06-12"}, {"yAxis": "38.53", "xAxis": "2026-06-15"}, {"yAxis": "38.43", "xAxis": "2026-06-16"}, {"yAxis": "36.88", "xAxis": "2026-06-17"}, {"yAxis": "34.31", "xAxis": "2026-06-18"}, {"yAxis": "34.24", "xAxis": "2026-06-22"}, {"yAxis": "31.61", "xAxis": "2026-06-23"}, {"yAxis": "28.18", "xAxis": "2026-06-24"}, {"yAxis": "28.94", "xAxis": "2026-06-25"}, {"yAxis": "28.54", "xAxis": "2026-06-26"}, {"yAxis": "27.86", "xAxis": "2026-06-29"}, {"yAxis": "27.67", "xAxis": "2026-06-30"}]