{
  "results": [
    {
      "name": "DCA-M20+TP50",
      "desc": "动量2.0+止盈50",
      "return": 37.70136666666668,
      "final_val": 82620.82,
      "total_in": 60000,
      "profit": 22620.820000000007,
      "dd": 2.5734701616874505,
      "trades": 162,
      "holdings": 4,
      "sharpe": 14.650011190316468,
      "fees": 726.85
    },
    {
      "name": "DCA-跟卖2人",
      "desc": "跟投+跟卖2人",
      "return": 107.50203333333333,
      "final_val": 124501.22,
      "total_in": 60000,
      "profit": 64501.22,
      "dd": 9.040812878879379,
      "trades": 67,
      "holdings": 17,
      "sharpe": 11.890748627755954,
      "fees": 82.88
    },
    {
      "name": "DCA-跟投原始",
      "desc": "原始无脑跟投",
      "return": 107.02906666666667,
      "final_val": 124217.44,
      "total_in": 60000,
      "profit": 64217.44,
      "dd": 9.040812878879379,
      "trades": 65,
      "holdings": 17,
      "sharpe": 11.83843401036446,
      "fees": 63.0
    },
    {
      "name": "DCA-净信号",
      "desc": "买入>卖出才买",
      "return": 107.02906666666667,
      "final_val": 124217.44,
      "total_in": 60000,
      "profit": 64217.44,
      "dd": 9.040812878879379,
      "trades": 65,
      "holdings": 17,
      "sharpe": 11.83843401036446,
      "fees": 63.0
    },
    {
      "name": "DCA-M20+分散10",
      "desc": "动量2.0+分散10",
      "return": 35.33273333333333,
      "final_val": 81199.64,
      "total_in": 60000,
      "profit": 21199.64,
      "dd": 3.433991154428459,
      "trades": 124,
      "holdings": 4,
      "sharpe": 10.289116000712,
      "fees": 700.23
    },
    {
      "name": "DCA-M20+TP30",
      "desc": "动量2.0+止盈30",
      "return": 26.15241666666666,
      "final_val": 75691.45,
      "total_in": 60000,
      "profit": 15691.449999999997,
      "dd": 2.5460378339715306,
      "trades": 181,
      "holdings": 4,
      "sharpe": 10.271809914887184,
      "fees": 679.43
    },
    {
      "name": "DCA-M20+分散15+TP30",
      "desc": "动量2.0+分散15+止盈30",
      "return": 20.55653333333333,
      "final_val": 72333.92,
      "total_in": 60000,
      "profit": 12333.919999999998,
      "dd": 2.0122894054824503,
      "trades": 190,
      "holdings": 4,
      "sharpe": 10.215495483565826,
      "fees": 724.17
    },
    {
      "name": "DCA-M20+分散15",
      "desc": "动量2.0+分散15",
      "return": 43.656516666666676,
      "final_val": 86193.91,
      "total_in": 60000,
      "profit": 26193.910000000003,
      "dd": 4.554740082315912,
      "trades": 112,
      "holdings": 4,
      "sharpe": 9.584853554249136,
      "fees": 684.56
    },
    {
      "name": "DCA-买卖对称3",
      "desc": "3人买+3人卖",
      "return": 78.23610000000001,
      "final_val": 106941.66,
      "total_in": 60000,
      "profit": 46941.66,
      "dd": 8.16922166206123,
      "trades": 50,
      "holdings": 13,
      "sharpe": 9.576934405310254,
      "fees": 49.05
    },
    {
      "name": "DCA-M20纯",
      "desc": "动量2.0卖出",
      "return": 66.43836666666667,
      "final_val": 99863.02,
      "total_in": 60000,
      "profit": 39863.020000000004,
      "dd": 8.101846332471363,
      "trades": 96,
      "holdings": 4,
      "sharpe": 8.20039827222945,
      "fees": 515.67
    },
    {
      "name": "DCA-M20+跟卖2",
      "desc": "动量2.0+跟卖2人",
      "return": 66.43836666666667,
      "final_val": 99863.02,
      "total_in": 60000,
      "profit": 39863.020000000004,
      "dd": 8.101846332471363,
      "trades": 96,
      "holdings": 4,
      "sharpe": 8.20039827222945,
      "fees": 515.67
    },
    {
      "name": "DCA-M20+跟卖3",
      "desc": "动量2.0+跟卖3人",
      "return": 66.43836666666667,
      "final_val": 99863.02,
      "total_in": 60000,
      "profit": 39863.020000000004,
      "dd": 8.101846332471363,
      "trades": 96,
      "holdings": 4,
      "sharpe": 8.20039827222945,
      "fees": 515.67
    },
    {
      "name": "DCA-M18纯",
      "desc": "动量1.8卖出",
      "return": 62.94408333333333,
      "final_val": 97766.45,
      "total_in": 60000,
      "profit": 37766.45,
      "dd": 8.109156416515512,
      "trades": 95,
      "holdings": 3,
      "sharpe": 7.762100038561135,
      "fees": 503.66
    },
    {
      "name": "DCA-M20+跟卖2+TP30+持仓5",
      "desc": "动量2.0+跟卖2+止盈30+持仓5",
      "return": 6.969566666666663,
      "final_val": 64181.74,
      "total_in": 60000,
      "profit": 4181.739999999998,
      "dd": 1.8972464699060256,
      "trades": 59,
      "holdings": 0,
      "sharpe": 3.673516739768597,
      "fees": 162.16
    },
    {
      "name": "纯定投不买基金",
      "desc": "每月3000只存钱不投资",
      "return": 0.0,
      "final_val": 60000,
      "total_in": 60000,
      "profit": 0,
      "dd": 0,
      "trades": 19,
      "holdings": 0,
      "sharpe": 0.0,
      "fees": 0
    }
  ],
  "period": "2025-01-05 ~ 2026-07-01",
  "monthly": 3000
}