{
  "date": "2026-06-26",
  "market": "bull",
  "min_score": 0.0,
  "candidates_top5": [
    {
      "code": "018147",
      "name": "建信新兴市场混合(QDII)C",
      "score": 2.8778810819600715
    },
    {
      "code": "008401",
      "name": "大成标普500等权重指数(QDII)C人民币",
      "score": 2.8764705882352937
    },
    {
      "code": "096001",
      "name": "大成标普500等权重指数(QDII)A人民币",
      "score": 2.8764705882352937
    },
    {
      "code": "519981",
      "name": "长信标普100等权重指数（QDII）人民币份额",
      "score": 2.8764705882352937
    },
    {
      "code": "001198",
      "name": "东方惠新灵活配置混合A",
      "score": 2.717647058823529
    }
  ],
  "buy_recommendations": [],
  "sell_recommendations": [],
  "blocked_funds": [
    {
      "code": "009995",
      "name": "嘉实创新先锋混合C",
      "reason": "RSI超买(76)"
    },
    {
      "code": "021511",
      "name": "宏利半导体产业混合发起C",
      "reason": "RSI超买(83)"
    },
    {
      "code": "013346",
      "name": "富荣信息技术混合C",
      "reason": "RSI超买(72)"
    },
    {
      "code": "025500",
      "name": "东方阿尔法科技智选混合发起C",
      "reason": "RSI超买(89)"
    },
    {
      "code": "015829",
      "name": "永赢新能源智选混合发起C",
      "reason": "RSI超买(72)"
    },
    {
      "code": "026211",
      "name": "平安科技精选混合发起式C",
      "reason": "RSI超买(71)"
    },
    {
      "code": "019018",
      "name": "易方达信息产业混合C",
      "reason": "RSI超买(72)"
    },
    {
      "code": "021528",
      "name": "财通成长优选混合C",
      "reason": "RSI超买(75)"
    },
    {
      "code": "006503",
      "name": "财通集成电路产业股票C",
      "reason": "RSI超买(74)"
    },
    {
      "code": "024481",
      "name": "财通品质甄选混合C",
      "reason": "RSI超买(76)"
    },
    {
      "code": "021523",
      "name": "财通价值动量混合C",
      "reason": "RSI超买(76)"
    },
    {
      "code": "013841",
      "name": "银华集成电路混合C",
      "reason": "RSI超买(90)"
    },
    {
      "code": "025209",
      "name": "永赢先锋半导体智选混合发起C",
      "reason": "RSI超买(89)"
    },
    {
      "code": "519674",
      "name": "银河创新混合A",
      "reason": "RSI超买(77)"
    },
    {
      "code": "501026",
      "name": "财通多策略福享混合(LOF)",
      "reason": "RSI超买(73)"
    },
    {
      "code": "008920",
      "name": "永赢科技驱动C",
      "reason": "RSI超买(78)"
    },
    {
      "code": "720001",
      "name": "财通价值动量混合A",
      "reason": "RSI超买(76)"
    },
    {
      "code": "009063",
      "name": "财通智慧成长混合C",
      "reason": "RSI超买(73)"
    },
    {
      "code": "024692",
      "name": "鑫元新兴产业睿选混合发起式C",
      "reason": "RSI超买(76)"
    },
    {
      "code": "015528",
      "name": "弘毅远方汽车产业升级混合C",
      "reason": "RSI超买(75)"
    },
    {
      "code": "017811",
      "name": "东方人工智能主题混合C",
      "reason": "RSI超买(92)"
    },
    {
      "code": "018816",
      "name": "方正富邦核心优势混合C",
      "reason": "RSI超买(87)"
    },
    {
      "code": "006523",
      "name": "财通新兴蓝筹混合C",
      "reason": "RSI超买(74)"
    },
    {
      "code": "025687",
      "name": "国泰半导体制造精选混合发起C",
      "reason": "RSI超买(94)"
    },
    {
      "code": "257070",
      "name": "国联安优选行业混合",
      "reason": "RSI超买(77)"
    },
    {
      "code": "006502",
      "name": "财通集成电路产业股票A",
      "reason": "RSI超买(74)"
    },
    {
      "code": "024481",
      "name": "财通品质甄选混合A",
      "reason": "RSI超买(76)"
    },
    {
      "code": "001480",
      "name": "财通成长优选混合A",
      "reason": "RSI超买(75)"
    },
    {
      "code": "019018",
      "name": "易方达信息产业混合A",
      "reason": "RSI超买(72)"
    },
    {
      "code": "008989",
      "name": "大成科技创新混合C",
      "reason": "RSI超买(76)"
    },
    {
      "code": "025547",
      "name": "财通周期优选混合C",
      "reason": "RSI超买(76)"
    }
  ],
  "holdings": {
    "025500": {
      "name": "东方阿尔法科技智选混合发起C",
      "cost": 33200,
      "market_value": 51203.43,
      "pnl_pct": 54.23
    },
    "021528": {
      "name": "财通成长优选混合C",
      "cost": 100.0,
      "market_value": 138.35,
      "pnl_pct": 38.35
    },
    "011452": {
      "name": "华泰柏瑞质量成长混合C",
      "cost": 10000.0,
      "market_value": 12721.19,
      "pnl_pct": 27.21
    },
    "022365": {
      "name": "永赢科技智选混合发起C",
      "cost": 18000,
      "market_value": 19073.88,
      "pnl_pct": 5.97
    },
    "017811": {
      "name": "东方人工智能主题混合C",
      "cost": 12000,
      "market_value": 18084.12,
      "pnl_pct": 50.7
    },
    "001608": {
      "name": "英大策略优选C",
      "cost": 8000,
      "market_value": 10188.35,
      "pnl_pct": 27.35
    },
    "021523": {
      "name": "财通价值动量混合C",
      "cost": 100.0,
      "market_value": 134.65,
      "pnl_pct": 34.65
    },
    "014581": {
      "name": "东吴阿尔法混合C",
      "cost": 5300,
      "market_value": 5729.23,
      "pnl_pct": 8.1
    },
    "016371": {
      "name": "信澳业绩驱动混合C",
      "cost": 3600,
      "market_value": 4448.8,
      "pnl_pct": 23.58
    },
    "018957": {
      "name": "中航机遇领航混合发起A",
      "cost": 2400,
      "market_value": 2666.12,
      "pnl_pct": 11.09
    },
    "024070": {
      "name": "上银中证半导体产业指数发起式C",
      "cost": 1600,
      "market_value": 1600,
      "pnl_pct": 0.0
    },
    "017496": {
      "name": "泰康中证科创创业50指数C",
      "cost": 1000,
      "market_value": 1000,
      "pnl_pct": 0.0
    },
    "017495": {
      "name": "泰康中证科创创业50指数A",
      "cost": 700,
      "market_value": 700,
      "pnl_pct": 0.0
    },
    "002112": {
      "name": "德邦鑫星价值C",
      "cost": 500,
      "market_value": 558.23,
      "pnl_pct": 11.65
    },
    "025209": {
      "name": "永赢先锋半导体智选混合发起C",
      "cost": 300,
      "market_value": 427.57,
      "pnl_pct": 42.52
    },
    "008702": {
      "name": "华夏黄金ETF联接C",
      "cost": 200,
      "market_value": 200,
      "pnl_pct": 0.0
    },
    "020988": {
      "name": "南方恒生科技ETF发起联接(QDII)A",
      "cost": 100,
      "market_value": 100,
      "pnl_pct": 0.0
    },
    "025687": {
      "name": "国泰半导体制造精选混合发起C",
      "cost": 100,
      "market_value": 152.1,
      "pnl_pct": 52.1
    },
    "015968": {
      "name": "永赢半导体产业智选混合发起C",
      "cost": 100,
      "market_value": 121.98,
      "pnl_pct": 21.98
    },
    "005698": {
      "name": "华夏全球科技先锋混合(QDII)A",
      "cost": 2500.0,
      "market_value": 2830.31,
      "pnl_pct": 13.21
    },
    "002891": {
      "name": "华夏移动互联混合(QDII)",
      "cost": 100.0,
      "market_value": 106.09,
      "pnl_pct": 6.09
    }
  },
  "fund_notices": {},
  "portfolio": {
    "total_value": 132284.4,
    "cash": 100.0,
    "fees": 7.47
  }
}